midiplot/__init__.py
midiplot/midiprocessing.py
midiplot-0.0b0.dist-info/LICENSE
midiplot-0.0b0.dist-info/METADATA
midiplot-0.0b0.dist-info/WHEEL
midiplot-0.0b0.dist-info/top_level.txt
midiplot-0.0b0.dist-info/RECORD
